CHANGES.rst
CONTRIBUTORS.rst
MANIFEST.in
README.rst
bootstrap.py
build_test.sh
setup.cfg
setup.py
test-4.0.x.cfg
test-4.1.x.cfg
test-4.2.x.cfg
test-4.3.x.cfg
docs/HISTORY.txt
docs/INSTALL.txt
docs/LICENSE.GPL
docs/LICENSE.txt
vs/__init__.py
vs.contentnavigation.egg-info/PKG-INFO
vs.contentnavigation.egg-info/SOURCES.txt
vs.contentnavigation.egg-info/dependency_links.txt
vs.contentnavigation.egg-info/entry_points.txt
vs.contentnavigation.egg-info/namespace_packages.txt
vs.contentnavigation.egg-info/not-zip-safe
vs.contentnavigation.egg-info/paster_plugins.txt
vs.contentnavigation.egg-info/requires.txt
vs.contentnavigation.egg-info/top_level.txt
vs/contentnavigation/README.txt
vs/contentnavigation/__init__.py
vs/contentnavigation/config.py
vs/contentnavigation/configure.zcml
vs/contentnavigation/browser/__init__.py
vs/contentnavigation/browser/configure.zcml
vs/contentnavigation/browser/folder.py
vs/contentnavigation/browser/folder_sitemap.pt
vs/contentnavigation/browser/sitemap_folder.pt
vs/contentnavigation/browser/viewlet_sitemap.pt
vs/contentnavigation/browser/resources/navigation-hide.css
vs/contentnavigation/browser/resources/navigation.css
vs/contentnavigation/browser/resources/navigation.js
vs/contentnavigation/browser/resources/toggle-open.png
vs/contentnavigation/browser/resources/toggle-right.png
vs/contentnavigation/browser/resources/toogle-open.png
vs/contentnavigation/browser/resources/toogle-right.png
vs/contentnavigation/browser/resources/jasmine/lib/stacktrace.js
vs/contentnavigation/browser/resources/jasmine/lib/jasmine-1.0.2/MIT.LICENSE
vs/contentnavigation/browser/resources/jasmine/lib/jasmine-1.0.2/jasmine-html.js
vs/contentnavigation/browser/resources/jasmine/lib/jasmine-1.0.2/jasmine.css
vs/contentnavigation/browser/resources/jasmine/lib/jasmine-1.0.2/jasmine.js
vs/contentnavigation/browser/resources/tests/CollapsibleTest.js
vs/contentnavigation/browser/resources/tests/SpecRunner.html
vs/contentnavigation/browser/resources/tests/jquery-1.4.4.min.js
vs/contentnavigation/browser/resources/tests/testHelpers.js
vs/contentnavigation/content/__init__.py
vs/contentnavigation/content/configure.zcml
vs/contentnavigation/extenders/__init__.py
vs/contentnavigation/extenders/configure.zcml
vs/contentnavigation/extenders/folder.py
vs/contentnavigation/interfaces/__init__.py
vs/contentnavigation/interfaces/interfaces.py
