Metadata-Version: 1.0
Name: vs.contentnavigation
Version: 0.2.3
Summary: vs.contentnavigation
Home-page: http://pypi.python.org/pypi/vs.contentnavigation
Author: Andreas Jung
Author-email: info@zopyx.com
License: GPL
Platform: UNKNOWN
Classifier: Framework :: Plone
Classifier: Framework :: Plone :: 4.0
Classifier: Framework :: Plone :: 4.1
Classifier: Framework :: Plone :: 4.2
Classifier: Framework :: Plone :: 4.3
Classifier: Intended Audience :: Developers
Classifier: License :: OSI Approved :: GNU General Public License (GPL)
